gno/__init__.py
gno/__main__.py
gno/cli.py
gno/merger.py
gno/templates.py
gno/tui.py
gno-0.1.0.dist-info/METADATA
gno-0.1.0.dist-info/WHEEL
gno-0.1.0.dist-info/entry_points.txt
gno-0.1.0.dist-info/licenses/LICENSE
gno-0.1.0.dist-info/RECORD
