Metadata-Version: 2.4
Name: gno
Version: 0.1.0
Summary: Interactive CLI tool for building .gitignore files
Project-URL: Homepage, https://github.com/OseSem/gno
Project-URL: Documentation, https://github.com/OseSem/gno#readme
Project-URL: Repository, https://github.com/OseSem/gno
Project-URL: Issues, https://github.com/OseSem/gno/issues
Project-URL: Changelog, https://github.com/OseSem/gno/blob/main/CHANGELOG.md
Author-email: OseSem <sem@osesem.xyz>
License: MIT
License-File: LICENSE
Keywords: cli,developer-tools,gitignore,interactive,tui
Classifier: Development Status :: 4 - Beta
Classifier: Environment :: Console
Classifier: Intended Audience :: Developers
Classifier: License :: OSI Approved :: MIT License
Classifier: Operating System :: OS Independent
Classifier: Programming Language :: Python :: 3
Classifier: Programming Language :: Python :: 3.10
Classifier: Programming Language :: Python :: 3.11
Classifier: Programming Language :: Python :: 3.12
Classifier: Programming Language :: Python :: 3.13
Classifier: Topic :: Software Development :: Version Control :: Git
Classifier: Topic :: Utilities
Requires-Python: >=3.10
Requires-Dist: click>=8.1.0
Requires-Dist: prompt-toolkit>=3.0.43
Requires-Dist: requests>=2.31.0
